pytoan/__init__.py
pytoan/contrib/__init__.py
pytoan/contrib/autoaugment.py
pytoan/pyplot/__init__.py
pytoan/pyplot/show.py
pytoan/pytorch/__init__.py
pytoan/pytorch/learning.py
pytoan/pytorch/utils/__init__.py
pytoan/pytorch/utils/util.py
pytoan/pytorch/utils/visualization.py
pytoan/sender/__init__.py
pytoan/sender/slack_sender.py
pytoan-0.7.2.2.9.dist-info/LICENSE
pytoan-0.7.2.2.9.dist-info/METADATA
pytoan-0.7.2.2.9.dist-info/WHEEL
pytoan-0.7.2.2.9.dist-info/top_level.txt
pytoan-0.7.2.2.9.dist-info/RECORD
