Metadata-Version: 2.1
Name: pytoan
Version: 0.7.2.2.9
Summary: A library of toandaominh1997
Home-page: https://github.com/toandaominh1997/pytoan
Author: toandaominh1997
Author-email: toandaominh1997@gmail.com
License: UNKNOWN
Platform: UNKNOWN
Classifier: Programming Language :: Python :: 3
Classifier: License :: OSI Approved :: MIT License
Classifier: Operating System :: OS Independent
